{
  "spx": {
    "slug": "spx",
    "symbol": "S&P 500",
    "name": "S&P 500 Index",
    "assetClass": "index",
    "currency": "USD",
    "price": 7408.5,
    "change": -92.7402,
    "changePct": -1.2363,
    "open": 7445.1099,
    "prevClose": 7501.2402,
    "dayHigh": 7454.8501,
    "dayLow": 7397.5,
    "high52w": 7517.1201,
    "low52w": 5767.4102,
    "history1w": [
      {
        "date": "2026-05-07",
        "close": 7337.1099
      },
      {
        "date": "2026-05-08",
        "close": 7398.9302
      },
      {
        "date": "2026-05-11",
        "close": 7412.8398
      },
      {
        "date": "2026-05-12",
        "close": 7400.96
      },
      {
        "date": "2026-05-13",
        "close": 7444.25
      },
      {
        "date": "2026-05-14",
        "close": 7501.2402
      },
      {
        "date": "2026-05-15",
        "close": 7408.5
      }
    ],
    "history1m": [
      {
        "date": "2026-04-06",
        "close": 6611.8301
      },
      {
        "date": "2026-04-07",
        "close": 6616.8501
      },
      {
        "date": "2026-04-08",
        "close": 6782.8101
      },
      {
        "date": "2026-04-09",
        "close": 6824.6602
      },
      {
        "date": "2026-04-10",
        "close": 6816.8901
      },
      {
        "date": "2026-04-13",
        "close": 6886.2402
      },
      {
        "date": "2026-04-14",
        "close": 6967.3799
      },
      {
        "date": "2026-04-15",
        "close": 7022.9502
      },
      {
        "date": "2026-04-16",
        "close": 7041.2798
      },
      {
        "date": "2026-04-17",
        "close": 7126.0601
      },
      {
        "date": "2026-04-20",
        "close": 7109.1401
      },
      {
        "date": "2026-04-21",
        "close": 7064.0098
      },
      {
        "date": "2026-04-22",
        "close": 7137.8999
      },
      {
        "date": "2026-04-23",
        "close": 7108.3999
      },
      {
        "date": "2026-04-24",
        "close": 7165.0801
      },
      {
        "date": "2026-04-27",
        "close": 7173.9102
      },
      {
        "date": "2026-04-28",
        "close": 7138.7998
      },
      {
        "date": "2026-04-29",
        "close": 7135.9502
      },
      {
        "date": "2026-04-30",
        "close": 7209.0098
      },
      {
        "date": "2026-05-01",
        "close": 7230.1201
      },
      {
        "date": "2026-05-04",
        "close": 7200.75
      },
      {
        "date": "2026-05-05",
        "close": 7259.2202
      },
      {
        "date": "2026-05-06",
        "close": 7365.1201
      },
      {
        "date": "2026-05-07",
        "close": 7337.1099
      },
      {
        "date": "2026-05-08",
        "close": 7398.9302
      },
      {
        "date": "2026-05-11",
        "close": 7412.8398
      },
      {
        "date": "2026-05-12",
        "close": 7400.96
      },
      {
        "date": "2026-05-13",
        "close": 7444.25
      },
      {
        "date": "2026-05-14",
        "close": 7501.2402
      },
      {
        "date": "2026-05-15",
        "close": 7408.5
      }
    ],
    "lastUpdated": "2026-05-17T14:02:47Z"
  },
  "dji": {
    "slug": "dji",
    "symbol": "DJIA",
    "name": "Dow Jones Industrial",
    "assetClass": "index",
    "currency": "USD",
    "price": 49526.1719,
    "change": -537.2891,
    "changePct": -1.0732,
    "open": 49930.2617,
    "prevClose": 50063.4609,
    "dayHigh": 49930.2617,
    "dayLow": 49503.5703,
    "high52w": 50512.7891,
    "low52w": 41354.0898,
    "history1w": [
      {
        "date": "2026-05-07",
        "close": 49596.9688
      },
      {
        "date": "2026-05-08",
        "close": 49609.1602
      },
      {
        "date": "2026-05-11",
        "close": 49704.4688
      },
      {
        "date": "2026-05-12",
        "close": 49760.5586
      },
      {
        "date": "2026-05-13",
        "close": 49693.1992
      },
      {
        "date": "2026-05-14",
        "close": 50063.4609
      },
      {
        "date": "2026-05-15",
        "close": 49526.1719
      }
    ],
    "history1m": [
      {
        "date": "2026-04-06",
        "close": 46669.8789
      },
      {
        "date": "2026-04-07",
        "close": 46584.4609
      },
      {
        "date": "2026-04-08",
        "close": 47909.9219
      },
      {
        "date": "2026-04-09",
        "close": 48185.8008
      },
      {
        "date": "2026-04-10",
        "close": 47916.5703
      },
      {
        "date": "2026-04-13",
        "close": 48218.25
      },
      {
        "date": "2026-04-14",
        "close": 48535.9883
      },
      {
        "date": "2026-04-15",
        "close": 48463.7188
      },
      {
        "date": "2026-04-16",
        "close": 48578.7188
      },
      {
        "date": "2026-04-17",
        "close": 49447.4297
      },
      {
        "date": "2026-04-20",
        "close": 49442.5586
      },
      {
        "date": "2026-04-21",
        "close": 49149.3789
      },
      {
        "date": "2026-04-22",
        "close": 49490.0312
      },
      {
        "date": "2026-04-23",
        "close": 49310.3203
      },
      {
        "date": "2026-04-24",
        "close": 49230.7109
      },
      {
        "date": "2026-04-27",
        "close": 49167.7891
      },
      {
        "date": "2026-04-28",
        "close": 49141.9297
      },
      {
        "date": "2026-04-29",
        "close": 48861.8086
      },
      {
        "date": "2026-04-30",
        "close": 49652.1406
      },
      {
        "date": "2026-05-01",
        "close": 49499.2695
      },
      {
        "date": "2026-05-04",
        "close": 48941.8984
      },
      {
        "date": "2026-05-05",
        "close": 49298.25
      },
      {
        "date": "2026-05-06",
        "close": 49910.5898
      },
      {
        "date": "2026-05-07",
        "close": 49596.9688
      },
      {
        "date": "2026-05-08",
        "close": 49609.1602
      },
      {
        "date": "2026-05-11",
        "close": 49704.4688
      },
      {
        "date": "2026-05-12",
        "close": 49760.5586
      },
      {
        "date": "2026-05-13",
        "close": 49693.1992
      },
      {
        "date": "2026-05-14",
        "close": 50063.4609
      },
      {
        "date": "2026-05-15",
        "close": 49526.1719
      }
    ],
    "lastUpdated": "2026-05-17T14:02:48Z"
  },
  "ixic": {
    "slug": "ixic",
    "symbol": "NASDAQ",
    "name": "Nasdaq Composite",
    "assetClass": "index",
    "currency": "USD",
    "price": 26225.1406,
    "change": -410.0801,
    "changePct": -1.5396,
    "open": 26288.9199,
    "prevClose": 26635.2207,
    "dayHigh": 26460.7598,
    "dayLow": 26097.5391,
    "high52w": 26707.1406,
    "low52w": 18599.6895,
    "history1w": [
      {
        "date": "2026-05-07",
        "close": 25806.1992
      },
      {
        "date": "2026-05-08",
        "close": 26247.0801
      },
      {
        "date": "2026-05-11",
        "close": 26274.1309
      },
      {
        "date": "2026-05-12",
        "close": 26088.1992
      },
      {
        "date": "2026-05-13",
        "close": 26402.3398
      },
      {
        "date": "2026-05-14",
        "close": 26635.2207
      },
      {
        "date": "2026-05-15",
        "close": 26225.1406
      }
    ],
    "history1m": [
      {
        "date": "2026-04-06",
        "close": 21996.3398
      },
      {
        "date": "2026-04-07",
        "close": 22017.8496
      },
      {
        "date": "2026-04-08",
        "close": 22634.9902
      },
      {
        "date": "2026-04-09",
        "close": 22822.4199
      },
      {
        "date": "2026-04-10",
        "close": 22902.8906
      },
      {
        "date": "2026-04-13",
        "close": 23183.7402
      },
      {
        "date": "2026-04-14",
        "close": 23639.0801
      },
      {
        "date": "2026-04-15",
        "close": 24016.0195
      },
      {
        "date": "2026-04-16",
        "close": 24102.6992
      },
      {
        "date": "2026-04-17",
        "close": 24468.4805
      },
      {
        "date": "2026-04-20",
        "close": 24404.3906
      },
      {
        "date": "2026-04-21",
        "close": 24259.9609
      },
      {
        "date": "2026-04-22",
        "close": 24657.5703
      },
      {
        "date": "2026-04-23",
        "close": 24438.5
      },
      {
        "date": "2026-04-24",
        "close": 24836.5996
      },
      {
        "date": "2026-04-27",
        "close": 24887.0996
      },
      {
        "date": "2026-04-28",
        "close": 24663.8008
      },
      {
        "date": "2026-04-29",
        "close": 24673.2402
      },
      {
        "date": "2026-04-30",
        "close": 24892.3105
      },
      {
        "date": "2026-05-01",
        "close": 25114.4395
      },
      {
        "date": "2026-05-04",
        "close": 25067.8008
      },
      {
        "date": "2026-05-05",
        "close": 25326.1309
      },
      {
        "date": "2026-05-06",
        "close": 25838.9395
      },
      {
        "date": "2026-05-07",
        "close": 25806.1992
      },
      {
        "date": "2026-05-08",
        "close": 26247.0801
      },
      {
        "date": "2026-05-11",
        "close": 26274.1309
      },
      {
        "date": "2026-05-12",
        "close": 26088.1992
      },
      {
        "date": "2026-05-13",
        "close": 26402.3398
      },
      {
        "date": "2026-05-14",
        "close": 26635.2207
      },
      {
        "date": "2026-05-15",
        "close": 26225.1406
      }
    ],
    "lastUpdated": "2026-05-17T14:02:48Z"
  },
  "btc": {
    "slug": "btc",
    "symbol": "BTC",
    "name": "Bitcoin",
    "assetClass": "crypto",
    "currency": "USD",
    "price": 78157.1484,
    "change": 25.7109,
    "changePct": 0.0329,
    "open": 78116.0312,
    "prevClose": 78131.4375,
    "dayHigh": 78507.9453,
    "dayLow": 77712.0625,
    "high52w": 126198.0703,
    "low52w": 60074.2031,
    "history1w": [
      {
        "date": "2026-05-11",
        "close": 81728.2969
      },
      {
        "date": "2026-05-12",
        "close": 80477.4922
      },
      {
        "date": "2026-05-13",
        "close": 79277.1172
      },
      {
        "date": "2026-05-14",
        "close": 81051.25
      },
      {
        "date": "2026-05-15",
        "close": 79065.6797
      },
      {
        "date": "2026-05-16",
        "close": 78131.4375
      },
      {
        "date": "2026-05-17",
        "close": 78157.1484
      }
    ],
    "history1m": [
      {
        "date": "2026-04-18",
        "close": 75726.2109
      },
      {
        "date": "2026-04-19",
        "close": 73856.3516
      },
      {
        "date": "2026-04-20",
        "close": 75872.5234
      },
      {
        "date": "2026-04-21",
        "close": 76352.7734
      },
      {
        "date": "2026-04-22",
        "close": 78203.1016
      },
      {
        "date": "2026-04-23",
        "close": 78268.9531
      },
      {
        "date": "2026-04-24",
        "close": 77455.3125
      },
      {
        "date": "2026-04-25",
        "close": 77612.0156
      },
      {
        "date": "2026-04-26",
        "close": 78657.5391
      },
      {
        "date": "2026-04-27",
        "close": 77366.625
      },
      {
        "date": "2026-04-28",
        "close": 76350.6719
      },
      {
        "date": "2026-04-29",
        "close": 75776.1328
      },
      {
        "date": "2026-04-30",
        "close": 76304.3203
      },
      {
        "date": "2026-05-01",
        "close": 78179.0
      },
      {
        "date": "2026-05-02",
        "close": 78657.25
      },
      {
        "date": "2026-05-03",
        "close": 78538.2266
      },
      {
        "date": "2026-05-04",
        "close": 79827.9062
      },
      {
        "date": "2026-05-05",
        "close": 80927.0547
      },
      {
        "date": "2026-05-06",
        "close": 81427.5312
      },
      {
        "date": "2026-05-07",
        "close": 80009.9922
      },
      {
        "date": "2026-05-08",
        "close": 80186.7656
      },
      {
        "date": "2026-05-09",
        "close": 80664.3672
      },
      {
        "date": "2026-05-10",
        "close": 82138.9297
      },
      {
        "date": "2026-05-11",
        "close": 81728.2969
      },
      {
        "date": "2026-05-12",
        "close": 80477.4922
      },
      {
        "date": "2026-05-13",
        "close": 79277.1172
      },
      {
        "date": "2026-05-14",
        "close": 81051.25
      },
      {
        "date": "2026-05-15",
        "close": 79065.6797
      },
      {
        "date": "2026-05-16",
        "close": 78131.4375
      },
      {
        "date": "2026-05-17",
        "close": 78157.1484
      }
    ],
    "lastUpdated": "2026-05-17T14:02:48Z",
    "volume24h": 18140987392.0
  },
  "eth": {
    "slug": "eth",
    "symbol": "ETH",
    "name": "Ethereum",
    "assetClass": "crypto",
    "currency": "USD",
    "price": 2190.6899,
    "change": 10.938,
    "changePct": 0.5018,
    "open": 2179.8201,
    "prevClose": 2179.752,
    "dayHigh": 2195.8677,
    "dayLow": 2168.9836,
    "high52w": 4953.7329,
    "low52w": 1748.6277,
    "history1w": [
      {
        "date": "2026-05-11",
        "close": 2339.3608
      },
      {
        "date": "2026-05-12",
        "close": 2274.6436
      },
      {
        "date": "2026-05-13",
        "close": 2257.5764
      },
      {
        "date": "2026-05-14",
        "close": 2280.9348
      },
      {
        "date": "2026-05-15",
        "close": 2223.3289
      },
      {
        "date": "2026-05-16",
        "close": 2179.752
      },
      {
        "date": "2026-05-17",
        "close": 2190.6899
      }
    ],
    "history1m": [
      {
        "date": "2026-04-18",
        "close": 2351.1006
      },
      {
        "date": "2026-04-19",
        "close": 2264.917
      },
      {
        "date": "2026-04-20",
        "close": 2315.2124
      },
      {
        "date": "2026-04-21",
        "close": 2327.9705
      },
      {
        "date": "2026-04-22",
        "close": 2376.0881
      },
      {
        "date": "2026-04-23",
        "close": 2331.5139
      },
      {
        "date": "2026-04-24",
        "close": 2315.6902
      },
      {
        "date": "2026-04-25",
        "close": 2318.8291
      },
      {
        "date": "2026-04-26",
        "close": 2369.729
      },
      {
        "date": "2026-04-27",
        "close": 2303.064
      },
      {
        "date": "2026-04-28",
        "close": 2289.4197
      },
      {
        "date": "2026-04-29",
        "close": 2253.4158
      },
      {
        "date": "2026-04-30",
        "close": 2256.2512
      },
      {
        "date": "2026-05-01",
        "close": 2295.0938
      },
      {
        "date": "2026-05-02",
        "close": 2316.2319
      },
      {
        "date": "2026-05-03",
        "close": 2321.6357
      },
      {
        "date": "2026-05-04",
        "close": 2346.397
      },
      {
        "date": "2026-05-05",
        "close": 2361.1826
      },
      {
        "date": "2026-05-06",
        "close": 2350.802
      },
      {
        "date": "2026-05-07",
        "close": 2291.1077
      },
      {
        "date": "2026-05-08",
        "close": 2306.9722
      },
      {
        "date": "2026-05-09",
        "close": 2326.7273
      },
      {
        "date": "2026-05-10",
        "close": 2369.0439
      },
      {
        "date": "2026-05-11",
        "close": 2339.3608
      },
      {
        "date": "2026-05-12",
        "close": 2274.6436
      },
      {
        "date": "2026-05-13",
        "close": 2257.5764
      },
      {
        "date": "2026-05-14",
        "close": 2280.9348
      },
      {
        "date": "2026-05-15",
        "close": 2223.3289
      },
      {
        "date": "2026-05-16",
        "close": 2179.752
      },
      {
        "date": "2026-05-17",
        "close": 2190.6899
      }
    ],
    "lastUpdated": "2026-05-17T14:02:48Z",
    "volume24h": 7762881536.0
  },
  "xau": {
    "slug": "xau",
    "symbol": "XAU",
    "name": "Gold Futures",
    "assetClass": "commodity",
    "currency": "USD",
    "price": 4561.8999,
    "change": -116.2002,
    "changePct": -2.4839,
    "open": 4654.5,
    "prevClose": 4678.1001,
    "dayHigh": 4670.1001,
    "dayLow": 4513.7998,
    "high52w": 5586.2002,
    "low52w": 3207.5,
    "history1w": [
      {
        "date": "2026-05-07",
        "close": 4699.7998
      },
      {
        "date": "2026-05-08",
        "close": 4720.3999
      },
      {
        "date": "2026-05-11",
        "close": 4718.7002
      },
      {
        "date": "2026-05-12",
        "close": 4677.6001
      },
      {
        "date": "2026-05-13",
        "close": 4697.7002
      },
      {
        "date": "2026-05-14",
        "close": 4678.1001
      },
      {
        "date": "2026-05-15",
        "close": 4561.8999
      }
    ],
    "history1m": [
      {
        "date": "2026-04-06",
        "close": 4656.7998
      },
      {
        "date": "2026-04-07",
        "close": 4657.1001
      },
      {
        "date": "2026-04-08",
        "close": 4749.5
      },
      {
        "date": "2026-04-09",
        "close": 4792.2002
      },
      {
        "date": "2026-04-10",
        "close": 4761.8999
      },
      {
        "date": "2026-04-13",
        "close": 4742.3999
      },
      {
        "date": "2026-04-14",
        "close": 4825.0
      },
      {
        "date": "2026-04-15",
        "close": 4800.0
      },
      {
        "date": "2026-04-16",
        "close": 4785.3999
      },
      {
        "date": "2026-04-17",
        "close": 4857.6001
      },
      {
        "date": "2026-04-20",
        "close": 4806.6001
      },
      {
        "date": "2026-04-21",
        "close": 4698.3999
      },
      {
        "date": "2026-04-22",
        "close": 4732.5
      },
      {
        "date": "2026-04-23",
        "close": 4705.1001
      },
      {
        "date": "2026-04-24",
        "close": 4722.2998
      },
      {
        "date": "2026-04-27",
        "close": 4675.3999
      },
      {
        "date": "2026-04-28",
        "close": 4591.5
      },
      {
        "date": "2026-04-29",
        "close": 4545.2002
      },
      {
        "date": "2026-04-30",
        "close": 4614.7002
      },
      {
        "date": "2026-05-01",
        "close": 4629.8999
      },
      {
        "date": "2026-05-04",
        "close": 4519.5
      },
      {
        "date": "2026-05-05",
        "close": 4555.7998
      },
      {
        "date": "2026-05-06",
        "close": 4681.8999
      },
      {
        "date": "2026-05-07",
        "close": 4699.7998
      },
      {
        "date": "2026-05-08",
        "close": 4720.3999
      },
      {
        "date": "2026-05-11",
        "close": 4718.7002
      },
      {
        "date": "2026-05-12",
        "close": 4677.6001
      },
      {
        "date": "2026-05-13",
        "close": 4697.7002
      },
      {
        "date": "2026-05-14",
        "close": 4678.1001
      },
      {
        "date": "2026-05-15",
        "close": 4561.8999
      }
    ],
    "lastUpdated": "2026-05-17T14:02:48Z"
  },
  "cl": {
    "slug": "cl",
    "symbol": "WTI",
    "name": "Crude Oil WTI",
    "assetClass": "commodity",
    "currency": "USD",
    "price": 101.02,
    "change": -0.15,
    "changePct": -0.1483,
    "open": 102.06,
    "prevClose": 101.17,
    "dayHigh": 101.57,
    "dayLow": 97.23,
    "high52w": 119.48,
    "low52w": 54.98,
    "history1w": [
      {
        "date": "2026-05-07",
        "close": 94.81
      },
      {
        "date": "2026-05-08",
        "close": 95.42
      },
      {
        "date": "2026-05-11",
        "close": 98.07
      },
      {
        "date": "2026-05-12",
        "close": 102.18
      },
      {
        "date": "2026-05-13",
        "close": 101.02
      },
      {
        "date": "2026-05-14",
        "close": 101.17
      },
      {
        "date": "2026-05-15",
        "close": 101.02
      }
    ],
    "history1m": [
      {
        "date": "2026-04-06",
        "close": 112.41
      },
      {
        "date": "2026-04-07",
        "close": 112.95
      },
      {
        "date": "2026-04-08",
        "close": 94.41
      },
      {
        "date": "2026-04-09",
        "close": 97.87
      },
      {
        "date": "2026-04-10",
        "close": 96.57
      },
      {
        "date": "2026-04-13",
        "close": 99.08
      },
      {
        "date": "2026-04-14",
        "close": 91.28
      },
      {
        "date": "2026-04-15",
        "close": 91.29
      },
      {
        "date": "2026-04-16",
        "close": 94.69
      },
      {
        "date": "2026-04-17",
        "close": 83.85
      },
      {
        "date": "2026-04-20",
        "close": 89.61
      },
      {
        "date": "2026-04-21",
        "close": 92.13
      },
      {
        "date": "2026-04-22",
        "close": 92.96
      },
      {
        "date": "2026-04-23",
        "close": 95.85
      },
      {
        "date": "2026-04-24",
        "close": 94.4
      },
      {
        "date": "2026-04-27",
        "close": 96.37
      },
      {
        "date": "2026-04-28",
        "close": 99.93
      },
      {
        "date": "2026-04-29",
        "close": 106.88
      },
      {
        "date": "2026-04-30",
        "close": 105.07
      },
      {
        "date": "2026-05-01",
        "close": 101.94
      },
      {
        "date": "2026-05-04",
        "close": 106.42
      },
      {
        "date": "2026-05-05",
        "close": 102.27
      },
      {
        "date": "2026-05-06",
        "close": 95.08
      },
      {
        "date": "2026-05-07",
        "close": 94.81
      },
      {
        "date": "2026-05-08",
        "close": 95.42
      },
      {
        "date": "2026-05-11",
        "close": 98.07
      },
      {
        "date": "2026-05-12",
        "close": 102.18
      },
      {
        "date": "2026-05-13",
        "close": 101.02
      },
      {
        "date": "2026-05-14",
        "close": 101.17
      },
      {
        "date": "2026-05-15",
        "close": 101.02
      }
    ],
    "lastUpdated": "2026-05-17T14:02:48Z"
  },
  "mntusd": {
    "slug": "mntusd",
    "symbol": "USD/MNT",
    "name": "Mongolian Tögrög",
    "assetClass": "forex",
    "currency": "MNT",
    "price": 3568.5649,
    "change": -0.1143,
    "changePct": -0.0032,
    "open": 3568.5649,
    "prevClose": 3568.6792,
    "dayHigh": 3568.5649,
    "dayLow": 3568.5649,
    "high52w": 3606.5879,
    "low52w": 3554.5408,
    "history1w": [
      {
        "date": "2026-05-11",
        "close": 3567.0957
      },
      {
        "date": "2026-05-12",
        "close": 3587.7738
      },
      {
        "date": "2026-05-13",
        "close": 3556.7975
      },
      {
        "date": "2026-05-14",
        "close": 3554.5408
      },
      {
        "date": "2026-05-15",
        "close": 3559.377
      },
      {
        "date": "2026-05-16",
        "close": 3568.6792
      },
      {
        "date": "2026-05-17",
        "close": 3568.5649
      }
    ],
    "history1m": [
      {
        "date": "2026-05-01",
        "close": 3588.1668
      },
      {
        "date": "2026-05-02",
        "close": 3591.8999
      },
      {
        "date": "2026-05-03",
        "close": 3589.8466
      },
      {
        "date": "2026-05-04",
        "close": 3593.9256
      },
      {
        "date": "2026-05-05",
        "close": 3593.2394
      },
      {
        "date": "2026-05-06",
        "close": 3577.8463
      },
      {
        "date": "2026-05-07",
        "close": 3606.5879
      },
      {
        "date": "2026-05-08",
        "close": 3559.3117
      },
      {
        "date": "2026-05-09",
        "close": 3566.7774
      },
      {
        "date": "2026-05-10",
        "close": 3566.9994
      },
      {
        "date": "2026-05-11",
        "close": 3567.0957
      },
      {
        "date": "2026-05-12",
        "close": 3587.7738
      },
      {
        "date": "2026-05-13",
        "close": 3556.7975
      },
      {
        "date": "2026-05-14",
        "close": 3554.5408
      },
      {
        "date": "2026-05-15",
        "close": 3559.377
      },
      {
        "date": "2026-05-16",
        "close": 3568.6792
      },
      {
        "date": "2026-05-17",
        "close": 3568.5649
      }
    ],
    "lastUpdated": "2026-05-17T14:02:48Z"
  },
  "msetop20": {
    "slug": "msetop20",
    "symbol": "MSE TOP-20",
    "name": "MSE Top 20 Index",
    "assetClass": "index",
    "currency": "MNT",
    "price": 50666.69,
    "change": -120.93,
    "changePct": -0.24,
    "open": 50666.69,
    "prevClose": 50787.62,
    "dayHigh": 50666.69,
    "dayLow": 50666.69,
    "high52w": 51397.55,
    "low52w": 50648.19,
    "history1w": [
      {
        "date": "2026-05-11",
        "close": 50835.94
      },
      {
        "date": "2026-05-12",
        "close": 50672.65
      },
      {
        "date": "2026-05-13",
        "close": 50648.19
      },
      {
        "date": "2026-05-14",
        "close": 50787.62
      },
      {
        "date": "2026-05-15",
        "close": 50666.69
      },
      {
        "date": "2026-05-16",
        "close": 50666.69
      },
      {
        "date": "2026-05-17",
        "close": 50666.69
      }
    ],
    "history1m": [
      {
        "date": "2026-05-02",
        "close": 51397.55
      },
      {
        "date": "2026-05-03",
        "close": 51397.55
      },
      {
        "date": "2026-05-04",
        "close": 51348.86
      },
      {
        "date": "2026-05-05",
        "close": 51147.75
      },
      {
        "date": "2026-05-06",
        "close": 50899.17
      },
      {
        "date": "2026-05-07",
        "close": 50764.08
      },
      {
        "date": "2026-05-08",
        "close": 50727.92
      },
      {
        "date": "2026-05-09",
        "close": 50843.33
      },
      {
        "date": "2026-05-10",
        "close": 50843.33
      },
      {
        "date": "2026-05-11",
        "close": 50835.94
      },
      {
        "date": "2026-05-12",
        "close": 50672.65
      },
      {
        "date": "2026-05-13",
        "close": 50648.19
      },
      {
        "date": "2026-05-14",
        "close": 50787.62
      },
      {
        "date": "2026-05-15",
        "close": 50666.69
      },
      {
        "date": "2026-05-16",
        "close": 50666.69
      },
      {
        "date": "2026-05-17",
        "close": 50666.69
      }
    ],
    "lastUpdated": "2026-05-17T14:02:49Z"
  }
}