{
  "fetched_at_utc": "2026-06-25T10:45:13Z",
  "fetched_at_mnt": "2026-06-25T18:45:13+08:00",
  "action_id_used": "6d867ebd99fb6edef2f9537b22668cd0c00a71c2",
  "rediscovered": false,
  "errors": [],
  "marquee": [
    {
      "symbol": "SUU",
      "price": 631.0,
      "change_pct": -0.02,
      "change_abs": -0.100015,
      "direction": "down"
    },
    {
      "symbol": "XAC",
      "price": 1299.0,
      "change_pct": 8.33,
      "change_abs": 100.0,
      "direction": "up"
    },
    {
      "symbol": "BAN",
      "price": 1599.0,
      "change_pct": -3.09,
      "change_abs": -51.0,
      "direction": "down"
    },
    {
      "symbol": "SBM",
      "price": 442.0,
      "change_pct": 0.27,
      "change_abs": 1.19999,
      "direction": "up"
    },
    {
      "symbol": "JTB",
      "price": 63.0,
      "change_pct": -2.83,
      "change_abs": -1.69,
      "direction": "down"
    },
    {
      "symbol": "HRM",
      "price": 180.0,
      "change_pct": 0.0,
      "change_abs": 0.0,
      "direction": "flat"
    },
    {
      "symbol": "SOH",
      "price": 900.0,
      "change_pct": -1.1,
      "change_abs": -10.0,
      "direction": "down"
    },
    {
      "symbol": "AARD",
      "price": 2921.0,
      "change_pct": -1.58,
      "change_abs": -49.0,
      "direction": "down"
    },
    {
      "symbol": "GRB",
      "price": 1.0,
      "change_pct": 0.0,
      "change_abs": 0.0,
      "direction": "flat"
    },
    {
      "symbol": "MFC",
      "price": 84.0,
      "change_pct": -4.54,
      "change_abs": -4.03,
      "direction": "down"
    },
    {
      "symbol": "GLMT",
      "price": 1160.0,
      "change_pct": 0.17,
      "change_abs": 2.0,
      "direction": "up"
    },
    {
      "symbol": "GAZR",
      "price": 39.58,
      "change_pct": -0.08,
      "change_abs": -0.0300006,
      "direction": "down"
    },
    {
      "symbol": "TDB",
      "price": 13940.0,
      "change_pct": 0.57,
      "change_abs": 80.0,
      "direction": "up"
    },
    {
      "symbol": "MNP",
      "price": 509.0,
      "change_pct": -1.98,
      "change_abs": -10.28,
      "direction": "down"
    },
    {
      "symbol": "APU",
      "price": 960.0,
      "change_pct": -1.47,
      "change_abs": -14.22,
      "direction": "down"
    },
    {
      "symbol": "AIC",
      "price": 661.68,
      "change_pct": 0.47,
      "change_abs": 3.10999,
      "direction": "up"
    },
    {
      "symbol": "TUM",
      "price": 372.0,
      "change_pct": 0.12,
      "change_abs": 0.44,
      "direction": "up"
    },
    {
      "symbol": "ADU",
      "price": 385.0,
      "change_pct": -1.28,
      "change_abs": -5.0,
      "direction": "down"
    },
    {
      "symbol": "KHAN",
      "price": 1459.0,
      "change_pct": 0.34,
      "change_abs": 5.0,
      "direction": "up"
    },
    {
      "symbol": "MBG",
      "price": 14.5,
      "change_pct": -14.71,
      "change_abs": -2.5,
      "direction": "down"
    },
    {
      "symbol": "TTL",
      "price": 32300.0,
      "change_pct": 0.62,
      "change_abs": 200.0,
      "direction": "up"
    },
    {
      "symbol": "BDL",
      "price": 15000.0,
      "change_pct": 3.45,
      "change_abs": 500.0,
      "direction": "up"
    },
    {
      "symbol": "ETR",
      "price": 117.29,
      "change_pct": 14.99,
      "change_abs": 15.29,
      "direction": "up"
    },
    {
      "symbol": "TAND",
      "price": 91.5,
      "change_pct": -0.54,
      "change_abs": -0.5,
      "direction": "down"
    },
    {
      "symbol": "ERS",
      "price": 23100.0,
      "change_pct": 0.0,
      "change_abs": 0.0,
      "direction": "flat"
    },
    {
      "symbol": "MGLA",
      "price": 296.0,
      "change_pct": 0.0,
      "change_abs": 0.0,
      "direction": "flat"
    },
    {
      "symbol": "MSE",
      "price": 367.0,
      "change_pct": -0.01,
      "change_abs": -0.03,
      "direction": "down"
    },
    {
      "symbol": "RMC",
      "price": 38.0,
      "change_pct": -10.18,
      "change_abs": -4.34,
      "direction": "down"
    },
    {
      "symbol": "AMT",
      "price": 7.12,
      "change_pct": -0.28,
      "change_abs": -0.0199999,
      "direction": "down"
    },
    {
      "symbol": "CUMN",
      "price": 272.0,
      "change_pct": 0.0,
      "change_abs": 0.0,
      "direction": "flat"
    },
    {
      "symbol": "SHNK",
      "price": 100.0,
      "change_pct": 0.0,
      "change_abs": 0.0,
      "direction": "flat"
    },
    {
      "symbol": "NEH",
      "price": 23.02,
      "change_pct": 3.74,
      "change_abs": 0.830001,
      "direction": "up"
    },
    {
      "symbol": "XOC",
      "price": 91.9,
      "change_pct": 9.4,
      "change_abs": 7.9,
      "direction": "up"
    },
    {
      "symbol": "MLG",
      "price": 140.0,
      "change_pct": 0.01,
      "change_abs": 0.0200043,
      "direction": "up"
    },
    {
      "symbol": "ADB",
      "price": 100.0,
      "change_pct": 0.09,
      "change_abs": 0.09,
      "direction": "up"
    },
    {
      "symbol": "MNDL",
      "price": 81.5,
      "change_pct": -0.44,
      "change_abs": -0.360003,
      "direction": "down"
    },
    {
      "symbol": "HSR",
      "price": 2213.0,
      "change_pct": 14.96,
      "change_abs": 288.0,
      "direction": "up"
    },
    {
      "symbol": "MFG",
      "price": 1078.0,
      "change_pct": 0.0,
      "change_abs": 0.0,
      "direction": "flat"
    },
    {
      "symbol": "LEND",
      "price": 153.89,
      "change_pct": 0.38,
      "change_abs": 0.579996,
      "direction": "up"
    },
    {
      "symbol": "MRX",
      "price": 27.0,
      "change_pct": -3.19,
      "change_abs": -0.889999,
      "direction": "down"
    },
    {
      "symbol": "SEND",
      "price": 143.99,
      "change_pct": 2.56,
      "change_abs": 3.6,
      "direction": "up"
    },
    {
      "symbol": "TGI",
      "price": 798.99,
      "change_pct": -0.36,
      "change_abs": -2.88,
      "direction": "down"
    },
    {
      "symbol": "MMX",
      "price": 4084.0,
      "change_pct": 13.44,
      "change_abs": 484.0,
      "direction": "up"
    },
    {
      "symbol": "BODI",
      "price": 76.99,
      "change_pct": -1.26,
      "change_abs": -0.980001,
      "direction": "down"
    },
    {
      "symbol": "AOI",
      "price": 2472.0,
      "change_pct": 14.98,
      "change_abs": 322.0,
      "direction": "up"
    },
    {
      "symbol": "HBO",
      "price": 54.5,
      "change_pct": -0.11,
      "change_abs": -0.0600014,
      "direction": "down"
    },
    {
      "symbol": "ALTT",
      "price": 4640.0,
      "change_pct": -2.32,
      "change_abs": -110.0,
      "direction": "down"
    },
    {
      "symbol": "GOV",
      "price": 222.0,
      "change_pct": 0.88,
      "change_abs": 1.96,
      "direction": "up"
    },
    {
      "symbol": "QPAY",
      "price": 275.0,
      "change_pct": 0.01,
      "change_abs": 0.02,
      "direction": "up"
    },
    {
      "symbol": "ITLS",
      "price": 78.99,
      "change_pct": -2.26,
      "change_abs": -1.74,
      "direction": "down"
    },
    {
      "symbol": "INV",
      "price": 7920.0,
      "change_pct": -0.06,
      "change_abs": -5.0,
      "direction": "down"
    },
    {
      "symbol": "SNDB",
      "price": 100.0,
      "change_pct": 0.0,
      "change_abs": 0.0,
      "direction": "flat"
    },
    {
      "symbol": "HRD",
      "price": 115000.0,
      "change_pct": 0.0,
      "change_abs": 0.0,
      "direction": "flat"
    },
    {
      "symbol": "MBW",
      "price": 159.01,
      "change_pct": -4.96,
      "change_abs": -8.39001,
      "direction": "down"
    },
    {
      "symbol": "BDS",
      "price": 2700.0,
      "change_pct": 0.0,
      "change_abs": 0.0,
      "direction": "flat"
    },
    {
      "symbol": "AZH",
      "price": 267500.0,
      "change_pct": -0.82,
      "change_abs": -1900.0,
      "direction": "down"
    },
    {
      "symbol": "ERDN",
      "price": 17200.0,
      "change_pct": -0.52,
      "change_abs": -90.0,
      "direction": "down"
    }
  ],
  "stock_amount": [
    {
      "symbol": "KHAN",
      "name": "Хаан банк ХК",
      "code": 563,
      "logo_url": "",
      "amount_mnt": 165732556.0,
      "change_pct": 0.34,
      "change_abs": 5.0,
      "direction": "up"
    },
    {
      "symbol": "APU",
      "name": "АПУ ХК",
      "code": 90,
      "logo_url": "",
      "amount_mnt": 60329957.3,
      "change_pct": -1.47,
      "change_abs": -14.22,
      "direction": "down"
    },
    {
      "symbol": "AZH",
      "name": "Алтайн зам ХК",
      "code": 227,
      "logo_url": "",
      "amount_mnt": 39747500.0,
      "change_pct": -0.82,
      "change_abs": -1900.0,
      "direction": "down"
    },
    {
      "symbol": "GLMT",
      "name": "Голомт Банк ХК",
      "code": 562,
      "logo_url": "",
      "amount_mnt": 29258902.0,
      "change_pct": 0.17,
      "change_abs": 2.0,
      "direction": "up"
    },
    {
      "symbol": "XAC",
      "name": "Хас Банк",
      "code": 568,
      "logo_url": "",
      "amount_mnt": 27163680.0,
      "change_pct": 8.33,
      "change_abs": 100.0,
      "direction": "up"
    },
    {
      "symbol": "TTL",
      "name": "Таван толгой ХК",
      "code": 458,
      "logo_url": "",
      "amount_mnt": 26485600.0,
      "change_pct": 0.62,
      "change_abs": 200.0,
      "direction": "up"
    },
    {
      "symbol": "AARD",
      "name": "Ард санхүүгийн нэгдэл ХК",
      "code": 326,
      "logo_url": "",
      "amount_mnt": 22427126.0,
      "change_pct": -1.58,
      "change_abs": -49.0,
      "direction": "down"
    },
    {
      "symbol": "INV",
      "name": "Инвескор ББСБ ХК",
      "code": 553,
      "logo_url": "",
      "amount_mnt": 19727475.0,
      "change_pct": -0.06,
      "change_abs": -5.0,
      "direction": "down"
    },
    {
      "symbol": "MSE",
      "name": "Монголын хөрөнгийн бирж ХК",
      "code": 510,
      "logo_url": "",
      "amount_mnt": 13005893.92,
      "change_pct": -0.01,
      "change_abs": -0.03,
      "direction": "down"
    },
    {
      "symbol": "TUM",
      "name": "Түмэн шувуут ХК",
      "code": 549,
      "logo_url": "",
      "amount_mnt": 9901787.43,
      "change_pct": 0.12,
      "change_abs": 0.44,
      "direction": "up"
    }
  ],
  "stock_up": [
    {
      "symbol": "ETR",
      "name": "Э-Транс ложистикс XК",
      "code": 537,
      "logo_url": "",
      "price": 117.29,
      "change_pct": 14.99,
      "change_abs": 15.29,
      "direction": "up"
    },
    {
      "symbol": "AOI",
      "name": "Авто импекс ХК",
      "code": 452,
      "logo_url": "",
      "price": 0.0,
      "change_pct": 14.98,
      "change_abs": 322.0,
      "direction": "up"
    },
    {
      "symbol": "HSR",
      "name": "Хасу-Мандал ХК",
      "code": 378,
      "logo_url": "",
      "price": 0.0,
      "change_pct": 14.96,
      "change_abs": 288.0,
      "direction": "up"
    },
    {
      "symbol": "MMX",
      "name": "Махимпекс ХК",
      "code": 208,
      "logo_url": "",
      "price": 0.0,
      "change_pct": 13.44,
      "change_abs": 484.0,
      "direction": "up"
    },
    {
      "symbol": "XAC",
      "name": "Хас Банк",
      "code": 568,
      "logo_url": "",
      "price": 0.0,
      "change_pct": 8.33,
      "change_abs": 100.0,
      "direction": "up"
    },
    {
      "symbol": "NEH",
      "name": "Дархан нэхий ХК",
      "code": 71,
      "logo_url": "",
      "price": 23.04,
      "change_pct": 3.74,
      "change_abs": 0.830001,
      "direction": "up"
    },
    {
      "symbol": "BDL",
      "name": "Могойн гол ХК",
      "code": 444,
      "logo_url": "",
      "price": 0.0,
      "change_pct": 3.45,
      "change_abs": 500.0,
      "direction": "up"
    },
    {
      "symbol": "SEND",
      "name": "Сэндли ББСБ ХК",
      "code": 561,
      "logo_url": "",
      "price": 143.99,
      "change_pct": 2.56,
      "change_abs": 3.6,
      "direction": "up"
    },
    {
      "symbol": "GOV",
      "name": "Говь ХК",
      "code": 354,
      "logo_url": "",
      "price": 223.65,
      "change_pct": 0.88,
      "change_abs": 1.96,
      "direction": "up"
    },
    {
      "symbol": "TTL",
      "name": "Таван толгой ХК",
      "code": 458,
      "logo_url": "",
      "price": 0.0,
      "change_pct": 0.62,
      "change_abs": 200.0,
      "direction": "up"
    }
  ],
  "stock_down": [
    {
      "symbol": "MBG",
      "name": "Булигаар ХК",
      "code": 38,
      "logo_url": "",
      "price": 14.5,
      "change_pct": -14.71,
      "change_abs": -2.5,
      "direction": "down"
    },
    {
      "symbol": "RMC",
      "name": "Ремикон ХК",
      "code": 530,
      "logo_url": "",
      "price": 38.28,
      "change_pct": -10.18,
      "change_abs": -4.34,
      "direction": "down"
    },
    {
      "symbol": "MBW",
      "name": "Монгол Базальт ХК",
      "code": 544,
      "logo_url": "",
      "price": 160.71,
      "change_pct": -4.96,
      "change_abs": -8.39001,
      "direction": "down"
    },
    {
      "symbol": "MFC",
      "name": "Монос хүнс ХК",
      "code": 551,
      "logo_url": "",
      "price": 84.72,
      "change_pct": -4.54,
      "change_abs": -4.03,
      "direction": "down"
    },
    {
      "symbol": "MRX",
      "name": "Мерекс ХК",
      "code": 540,
      "logo_url": "",
      "price": 27.0,
      "change_pct": -3.19,
      "change_abs": -0.889999,
      "direction": "down"
    },
    {
      "symbol": "BAN",
      "name": "Багануур ХК",
      "code": 396,
      "logo_url": "",
      "price": 0.0,
      "change_pct": -3.09,
      "change_abs": -51.0,
      "direction": "down"
    },
    {
      "symbol": "JTB",
      "name": "Женко тур бюро ХК",
      "code": 521,
      "logo_url": "",
      "price": 58.01,
      "change_pct": -2.83,
      "change_abs": -1.69,
      "direction": "down"
    },
    {
      "symbol": "ITLS",
      "name": "Айтүүлс ХК",
      "code": 543,
      "logo_url": "",
      "price": 75.26,
      "change_pct": -2.26,
      "change_abs": -1.74,
      "direction": "down"
    },
    {
      "symbol": "MNP",
      "name": "Монгол шуудан ХК",
      "code": 541,
      "logo_url": "",
      "price": 509.72,
      "change_pct": -1.98,
      "change_abs": -10.28,
      "direction": "down"
    },
    {
      "symbol": "AARD",
      "name": "Ард санхүүгийн нэгдэл ХК",
      "code": 326,
      "logo_url": "",
      "price": 0.0,
      "change_pct": -1.58,
      "change_abs": -49.0,
      "direction": "down"
    }
  ],
  "comex_trade": [
    {
      "id": 4211,
      "main_type": "Нүүрс",
      "category": "Баяжуулсан дунд зэрэг үнстэй, хагас хатуу коксжих нүүрс",
      "seller": "Энержи Ресурс ХХК",
      "started_at": "2026-06-25T14:00:00",
      "min_price": 450.0,
      "price": 460.0,
      "currency": "CNY",
      "change_abs": 10.0,
      "change_pct": 2.22,
      "direction": "up"
    },
    {
      "id": 4208,
      "main_type": "Нүүрс",
      "category": "1/3 коксжих нүүрс",
      "seller": "Эрдэнэс Тавантолгой ХК",
      "started_at": "2026-06-25T10:00:00",
      "min_price": 99.0,
      "price": 109.0,
      "currency": "USD",
      "change_abs": 10.0,
      "change_pct": 10.1,
      "direction": "up"
    },
    {
      "id": 4207,
      "main_type": "Нүүрс",
      "category": "1/3 коксжих нүүрс",
      "seller": "Тавантолгой ХК",
      "started_at": "2026-06-24T14:00:00",
      "min_price": 105.0,
      "price": 135.5,
      "currency": "USD",
      "change_abs": 30.5,
      "change_pct": 29.05,
      "direction": "up"
    },
    {
      "id": 4206,
      "main_type": "Нүүрс",
      "category": "Баяжуулсан дунд зэрэг үнстэй, хагас хатуу коксжих нүүрс",
      "seller": "Энержи Ресурс ХХК",
      "started_at": "2026-06-24T14:00:00",
      "min_price": 450.0,
      "price": 460.0,
      "currency": "CNY",
      "change_abs": 10.0,
      "change_pct": 2.22,
      "direction": "up"
    },
    {
      "id": 4205,
      "main_type": "Нүүрс",
      "category": "1/3 коксжих нүүрс",
      "seller": "Тавантолгой ХК",
      "started_at": "2026-06-24T12:00:00",
      "min_price": 105.0,
      "price": 136.5,
      "currency": "USD",
      "change_abs": 31.5,
      "change_pct": 30.0,
      "direction": "up"
    }
  ],
  "mseA_list": [
    {
      "row": 1,
      "symbol": "AARD",
      "name": "Ард санхүүгийн нэгдэл ХК",
      "code": 326
    },
    {
      "row": 2,
      "symbol": "ADB",
      "name": "Ард кредит ББСБ ХК",
      "code": 550
    },
    {
      "row": 3,
      "symbol": "AIC",
      "name": "Ард Даатгал ХК",
      "code": 548
    },
    {
      "row": 4,
      "symbol": "APU",
      "name": "АПУ ХК",
      "code": 90
    },
    {
      "row": 5,
      "symbol": "BDS",
      "name": "Би ди сек ХК",
      "code": 522
    },
    {
      "row": 6,
      "symbol": "CUMN",
      "name": "Премиум Нэксус ХК",
      "code": 557
    },
    {
      "row": 7,
      "symbol": "GLMT",
      "name": "Голомт Банк ХК",
      "code": 562
    },
    {
      "row": 8,
      "symbol": "GOV",
      "name": "Говь ХК",
      "code": 354
    },
    {
      "row": 9,
      "symbol": "INV",
      "name": "Инвескор ББСБ ХК",
      "code": 553
    },
    {
      "row": 10,
      "symbol": "KHAN",
      "name": "Хаан банк ХК",
      "code": 563
    },
    {
      "row": 11,
      "symbol": "LEND",
      "name": "ЛэндМН ББСБ ХК",
      "code": 545
    },
    {
      "row": 12,
      "symbol": "MBW",
      "name": "Монгол Базальт ХК",
      "code": 544
    },
    {
      "row": 13,
      "symbol": "MFC",
      "name": "Монос хүнс ХК",
      "code": 551
    },
    {
      "row": 14,
      "symbol": "MIK",
      "name": "Мик холдинг ХК",
      "code": 542
    },
    {
      "row": 15,
      "symbol": "MLG",
      "name": "Монложистикс Холдинг ХК",
      "code": 569
    },
    {
      "row": 16,
      "symbol": "MNDL",
      "name": "Мандал Даатгал ХК",
      "code": 547
    },
    {
      "row": 17,
      "symbol": "MNP",
      "name": "Монгол шуудан ХК",
      "code": 541
    },
    {
      "row": 18,
      "symbol": "MSE",
      "name": "Монголын хөрөнгийн бирж ХК",
      "code": 510
    },
    {
      "row": 19,
      "symbol": "NEH",
      "name": "Дархан нэхий ХК",
      "code": 71
    },
    {
      "row": 20,
      "symbol": "SBM",
      "name": "Төрийн Банк ХК",
      "code": 564
    },
    {
      "row": 21,
      "symbol": "SUU",
      "name": "Сүү ХК",
      "code": 135
    },
    {
      "row": 22,
      "symbol": "TDB",
      "name": "Худалдаа Хөгжлийн банк",
      "code": 567
    },
    {
      "row": 23,
      "symbol": "TTL",
      "name": "Таван толгой ХК",
      "code": 458
    },
    {
      "row": 24,
      "symbol": "TUM",
      "name": "Түмэн шувуут ХК",
      "code": 549
    },
    {
      "row": 25,
      "symbol": "XAC",
      "name": "Хас Банк",
      "code": 568
    }
  ],
  "mseB_list": [
    {
      "row": 1,
      "symbol": "ADU",
      "name": "Хөвсгөл алтан дуулга ХК",
      "code": 402
    },
    {
      "row": 2,
      "symbol": "ATR",
      "name": "Атар-Өргөө ХК",
      "code": 17
    },
    {
      "row": 3,
      "symbol": "BAN",
      "name": "Багануур ХК",
      "code": 396
    },
    {
      "row": 4,
      "symbol": "BDL",
      "name": "Могойн гол ХК",
      "code": 444
    },
    {
      "row": 5,
      "symbol": "BNG",
      "name": "Баянгол зочид буудал ХК",
      "code": 13
    },
    {
      "row": 6,
      "symbol": "BODI",
      "name": "Бодь Даатгал ХК",
      "code": 554
    },
    {
      "row": 7,
      "symbol": "BOE",
      "name": "Эрчим Баян Өлгий ХК",
      "code": 466
    },
    {
      "row": 8,
      "symbol": "BTG",
      "name": "Баянтээг ХК",
      "code": 445
    },
    {
      "row": 9,
      "symbol": "BUK",
      "name": "Улаанбаатар БҮК ХК",
      "code": 195
    },
    {
      "row": 10,
      "symbol": "CNF",
      "name": "Крипто Үндэстэн ХК",
      "code": 308
    },
    {
      "row": 11,
      "symbol": "DZG",
      "name": "Дархан зочид буудал ХК",
      "code": 366
    },
    {
      "row": 12,
      "symbol": "EER",
      "name": "Ариг гал ХК",
      "code": 191
    },
    {
      "row": 13,
      "symbol": "ERDN",
      "name": "Эрдэнэ Ресурс Девелопмент Корпорэйшн",
      "code": 546
    },
    {
      "row": 14,
      "symbol": "ETR",
      "name": "Э-Транс ложистикс XК",
      "code": 537
    },
    {
      "row": 15,
      "symbol": "GAZR",
      "name": "Газар Шим Үйлдвэр ХК",
      "code": 565
    },
    {
      "row": 16,
      "symbol": "GHC",
      "name": "Ган хийц ХК",
      "code": 234
    },
    {
      "row": 17,
      "symbol": "GTL",
      "name": "Гутал ХК",
      "code": 88
    },
    {
      "row": 18,
      "symbol": "HBO",
      "name": "Хай би ойл ХК",
      "code": 525
    },
    {
      "row": 19,
      "symbol": "HRM",
      "name": "Гермес центр ХК",
      "code": 528
    },
    {
      "row": 20,
      "symbol": "HSR",
      "name": "Хасу-Мандал ХК",
      "code": 378
    },
    {
      "row": 21,
      "symbol": "ITLS",
      "name": "Айтүүлс ХК",
      "code": 543
    },
    {
      "row": 22,
      "symbol": "JTB",
      "name": "Женко тур бюро ХК",
      "code": 521
    },
    {
      "row": 23,
      "symbol": "MBG",
      "name": "Булигаар ХК",
      "code": 38
    },
    {
      "row": 24,
      "symbol": "MCH",
      "name": "Монголын цахилгаан холбоо ХК",
      "code": 209
    },
    {
      "row": 25,
      "symbol": "MDIC",
      "name": "Монгол даатгал ХК",
      "code": 162
    },
    {
      "row": 26,
      "symbol": "MGLA",
      "name": "Эм Жи Эл Акуа ХК",
      "code": 572
    },
    {
      "row": 27,
      "symbol": "MIB",
      "name": "Монинжбар ХК",
      "code": 25
    },
    {
      "row": 28,
      "symbol": "MIE",
      "name": "Материалимпекс ХК",
      "code": 379
    },
    {
      "row": 29,
      "symbol": "MMX",
      "name": "Махимпекс ХК",
      "code": 208
    },
    {
      "row": 30,
      "symbol": "MNH",
      "name": "Монгол нэхмэл ХК",
      "code": 9
    },
    {
      "row": 31,
      "symbol": "QPAY",
      "name": "Инновэйшн инвестмент ХК",
      "code": 570
    },
    {
      "row": 32,
      "symbol": "RMC",
      "name": "Ремикон ХК",
      "code": 530
    },
    {
      "row": 33,
      "symbol": "SEND",
      "name": "Сэндли ББСБ ХК",
      "code": 561
    },
    {
      "row": 34,
      "symbol": "SHG",
      "name": "Шарын гол ХК",
      "code": 309
    },
    {
      "row": 35,
      "symbol": "SHV",
      "name": "Шивээ овоо ХК",
      "code": 460
    },
    {
      "row": 36,
      "symbol": "SUL",
      "name": "Жуулчин дюти фрий ХК",
      "code": 34
    },
    {
      "row": 37,
      "symbol": "TAND",
      "name": "Тандэм инвэст ББСБ ХК",
      "code": 438
    },
    {
      "row": 38,
      "symbol": "TCK",
      "name": "Талх чихэр ХК",
      "code": 22
    },
    {
      "row": 39,
      "symbol": "TEX",
      "name": "Техник импорт ХК",
      "code": 441
    },
    {
      "row": 40,
      "symbol": "TGI",
      "name": "Тэнгэр Даатгал ХК",
      "code": 573
    },
    {
      "row": 41,
      "symbol": "UBH",
      "name": "Улаанбаатар хивс ХК",
      "code": 7
    },
    {
      "row": 42,
      "symbol": "UID",
      "name": "Улсын их дэлгүүр ХК",
      "code": 484
    },
    {
      "row": 43,
      "symbol": "UYN",
      "name": "Монгол савхи ХК",
      "code": 2
    }
  ],
  "top20_list": [
    {
      "row": 1,
      "symbol": "AARD",
      "name": "Ард санхүүгийн нэгдэл ХК",
      "code": 326
    },
    {
      "row": 2,
      "symbol": "APU",
      "name": "АПУ ХК",
      "code": 90
    },
    {
      "row": 3,
      "symbol": "CUMN",
      "name": "Премиум Нэксус ХК",
      "code": 557
    },
    {
      "row": 4,
      "symbol": "GLMT",
      "name": "Голомт Банк ХК",
      "code": 562
    },
    {
      "row": 5,
      "symbol": "GOV",
      "name": "Говь ХК",
      "code": 354
    },
    {
      "row": 6,
      "symbol": "INV",
      "name": "Инвескор ББСБ ХК",
      "code": 553
    },
    {
      "row": 7,
      "symbol": "KHAN",
      "name": "Хаан банк ХК",
      "code": 563
    },
    {
      "row": 8,
      "symbol": "LEND",
      "name": "ЛэндМН ББСБ ХК",
      "code": 545
    },
    {
      "row": 9,
      "symbol": "MGLA",
      "name": "Эм Жи Эл Акуа ХК",
      "code": 572
    },
    {
      "row": 10,
      "symbol": "MLG",
      "name": "Монложистикс Холдинг ХК",
      "code": 569
    },
    {
      "row": 11,
      "symbol": "MNDL",
      "name": "Мандал Даатгал ХК",
      "code": 547
    },
    {
      "row": 12,
      "symbol": "MSE",
      "name": "Монголын хөрөнгийн бирж ХК",
      "code": 510
    },
    {
      "row": 13,
      "symbol": "QPAY",
      "name": "Инновэйшн инвестмент ХК",
      "code": 570
    },
    {
      "row": 14,
      "symbol": "SBM",
      "name": "Төрийн Банк ХК",
      "code": 564
    },
    {
      "row": 15,
      "symbol": "SUU",
      "name": "Сүү ХК",
      "code": 135
    },
    {
      "row": 16,
      "symbol": "TDB",
      "name": "Худалдаа Хөгжлийн банк",
      "code": 567
    },
    {
      "row": 17,
      "symbol": "TTL",
      "name": "Таван толгой ХК",
      "code": 458
    },
    {
      "row": 18,
      "symbol": "TUM",
      "name": "Түмэн шувуут ХК",
      "code": 549
    },
    {
      "row": 19,
      "symbol": "UID",
      "name": "Улсын их дэлгүүр ХК",
      "code": 484
    },
    {
      "row": 20,
      "symbol": "XAC",
      "name": "Хас Банк",
      "code": 568
    }
  ],
  "elapsed_seconds": 7.1
}